mobio/libs/validate_import_file
